modules/VrDff/rtl/VrDff.v
module VrDff (
    input CLK,
    input D,
    output reg Q
);

always @(posedge CLK) 
    Q <= D;
endmodule

modules/VrDff/tb/VrDff_tb.v
`timescale 1ns/1ns

module tb_VrDff;

    reg CLK;
    reg D;
    wire Q;

    VrDff dut (
        .CLK(CLK),
        .D(D),
        .Q(Q)
    );

    initial begin
        $dumpfile("VrDff.vcd");
        $dumpvars(0, tb_VrDff);
        $monitor("t=%0t CLK=%b D=%b | Q=%b", $time, CLK, D, Q);
       
        CLK = 0;
        forever #5 CLK = ~CLK; 
        D = 0; #10;
        D = 1; #10;
        D = 0; #10;
        D = 1; #10;
        D = 0; #10;
        D = 1; #10;
    end

endmodule

modules/VrDff/resultados/VrDff.vcd
$date
	Thu Mar 26 22:17:10 2026
$end
$version
	Icarus Verilog
$end
$timescale
	1ns
$end
$scope module tb_VrDff $end
$var wire 1 ! Q $end
$var reg 1 " CLK $end
$var reg 1 # D $end
$scope module dut $end
$var wire 1 " CLK $end
$var wire 1 # D $end
$var reg 1 ! Q $end
$upscope $end
$upscope $end
$enddefinitions $end
$comment Show the parameter values. $end
$dumpall
$end
#0
$dumpvars
0#
0"
x!
$end
#5
0!
1"
#10
0"
1#
#15
1!
1"
#20
0"
0#
#25
0!
1"
#30
0"
1#
#35
1!
1"
#40
0"
0#
#45
0!
1"
#50
0"
1#
#55
1!
1"
