modules/VrDffC/rtl/VrDffC.v
module VrDffC (
    input CLK,
    input CLR,
    input D,
    output reg Q
);

    always @(posedge CLK or posedge CLR) begin
        if (CLR==1) Q <= 0;
        else Q <= D;
    end

endmodule

modules/VrDffC/tb/VrDffC_tb.v
`timescale 1ns/1ns

module tb_VrDffC;
    reg CLK;
    reg RESET;
    reg DATA_IN;
    wire DATA_OUT;

    VrDffC dut (
        .CLK(CLK),
        .CLR(RESET),
        .D(DATA_IN),
        .Q(DATA_OUT)
    );

    initial CLK = 0;
    always #5 CLK = ~CLK; 


    initial begin
        $dumpfile("VrDffC.vcd");
        $dumpvars(0, tb_VrDffC);
        $monitor("t=%0t CLK=%b CLR=%b D=%b | Q=%b", $time, CLK, RESET, DATA_IN, DATA_OUT);
        // Teste de reset
        RESET = 1; DATA_IN = 0; #10;
        RESET = 0; #10;
        // Teste de operação normal
        DATA_IN = 1; #10;
        DATA_IN = 0; #10;
        DATA_IN = 1; #10;
        DATA_IN = 0; #10;
        DATA_IN = 1; #10;
        // Teste de reset durante operação
        RESET = 1; #10;
        RESET = 0; #10;
        DATA_IN = 1; #10;
        DATA_IN = 0; #10;
    $finish;
        
        
   end

endmodule

modules/VrDffC/resultados/VrDffC.vcd
$date
	Thu Mar 26 22:17:10 2026
$end
$version
	Icarus Verilog
$end
$timescale
	1ns
$end
$scope module tb_VrDffC $end
$var wire 1 ! DATA_OUT $end
$var reg 1 " CLK $end
$var reg 1 # DATA_IN $end
$var reg 1 $ RESET $end
$scope module dut $end
$var wire 1 " CLK $end
$var wire 1 $ CLR $end
$var wire 1 # D $end
$var reg 1 ! Q $end
$upscope $end
$upscope $end
$enddefinitions $end
$comment Show the parameter values. $end
$dumpall
$end
#0
$dumpvars
1$
0#
0"
0!
$end
#5
1"
#10
0"
0$
#15
1"
#20
0"
1#
#25
1!
1"
#30
0"
0#
#35
0!
1"
#40
0"
1#
#45
1!
1"
#50
0"
0#
#55
0!
1"
#60
0"
1#
#65
1!
1"
#70
0!
0"
1$
#75
1"
#80
0"
0$
#85
1!
1"
#90
0"
#95
1"
#100
0"
0#
#105
0!
1"
