modules/VrDlatch/rtl/VrDlatch.v
module VrDlatch (
    input D,       
    input G,       
    output reg Q
);

  always @(D or G) begin
    if (G == 1'b1) begin
        Q <= D;
    end
end
    
endmodule

modules/VrDlatch/tb/VrDlatch.v
`timescale 1ns/1ns 

module tb_VrDlatch;

  reg D;
  reg G;
  wire Q;

  VrDlatch dut (
    .D(D),
    .G(G),
    .Q(Q)
  );

  initial begin
    $dumpfile("VrDlatch.vcd");
    $dumpvars(0, tb_VrDlatch);
    $monitor("t=%0t D=%b G=%b | Q=%b", $time, D, G, Q);

    D = 0; G = 0; #10;
    D = 1; G = 0; #10;
    D = 0; G = 1; #10;
    D = 1; G = 1; #10;
    D = 0; G = 0; #10;
    D = 1; G = 0; #10;
    D = 0; G = 1; #10;
    D = 1; G = 1; #10;

    $finish;
  end

endmodule

modules/VrDlatch/resultados/VrDlatch.vcd
$date
	Sat Apr 04 15:36:53 2026
$end
$version
	Icarus Verilog
$end
$timescale
	1ns
$end
$scope module tb_VrDlatch $end
$var wire 1 ! Q $end
$var reg 1 " D $end
$var reg 1 # G $end
$scope module dut $end
$var wire 1 " D $end
$var wire 1 # G $end
$var reg 1 ! Q $end
$upscope $end
$upscope $end
$enddefinitions $end
$comment Show the parameter values. $end
$dumpall
$end
#0
$dumpvars
0#
0"
x!
$end
#10
1"
#20
0!
1#
0"
#30
1!
1"
#40
0#
0"
#50
1"
#60
0!
1#
0"
#70
1!
1"
